{
    "bootsrapProperties": [
        {"key": "ledger.id", "value": "0x01"},
        {"key": "netty.mode", "value": "DEV"},
        {"key": "contracts.chainId", "value": "298"},
        {"key": "hedera.recordStream.logPeriod", "value": "1"},
        {"key": "balances.exportPeriodSecs", "value": "400"},
        {"key": "blockStream.streamMode", "value": "RECORDS"},
        {"key": "blockStream.writerMode", "value": "FILE"},
        {"key": "blockStream.buffer.isBufferPersistenceEnabled", "value": false},
        {"key": "hedera.recordStream.writeWrappedRecordFileBlockHashesToDisk", "value": false},
        {"key": "hedera.recordStream.computeHashesFromWrappedRecordBlocks", "value": false},
        {"key": "hedera.recordStream.liveWritePrevWrappedRecordHashes", "value": false},
        {"key": "tss.enableCutover", "value": false},
        {"key": "tss.hintsEnabled", "value": false},
        {"key": "tss.historyEnabled", "value": false},
        {"key": "tss.wrapsEnabled", "value": false}
    ],
    "fullNodeProperties": [
        {
          "accountId": "0.0.3",
          "host": "network-node",
          "nodeId": 0

        }
    ],
    "turboNodeProperties": {
        "dataPath": "file:///node/",
        "sources": [{ "type": "LOCAL" }]
    },
    "multiNodeProperties": [
        {
            "accountId": "0.0.3",
            "host": "network-node",
            "nodeId": 0
        },
        {
            "accountId": "0.0.4",
            "host": "network-node-1",
            "nodeId": 1
        },
        {
            "accountId": "0.0.5",
            "host": "network-node-2",
            "nodeId": 2
        },
        {
            "accountId": "0.0.6",
            "host": "network-node-3",
            "nodeId": 3
        }
    ],
    "local": {
        "deleteAfterProcessing": false
    }
}
